synk/__init__.py
synk-0.0.1.dist-info/LICENSE
synk-0.0.1.dist-info/METADATA
synk-0.0.1.dist-info/WHEEL
synk-0.0.1.dist-info/top_level.txt
synk-0.0.1.dist-info/RECORD
