Metadata-Version: 2.1
Name: synk
Version: 0.0.1
Summary: synk command line interface and related libraries
Home-page: https://github.com/synksuite/synk-cli
Author: Jimmy Dias
Author-email: jimmy@synksuite.com
License: UNKNOWN
Platform: UNKNOWN
Classifier: Programming Language :: Python :: 3
Classifier: License :: OSI Approved :: MIT License
Classifier: Operating System :: OS Independent
